{
  "type": "object",
  "title": "ApplicationSourceJsonnet holds options specific to applications of type Jsonnet",
  "properties": {
    "extVars": {
      "type": "array",
      "title": "ExtVars is a list of Jsonnet External Variables",
      "items": {
        "$ref": "_definitions.json#/definitions/v1alpha1JsonnetVar"
      }
    },
    "libs": {
      "type": "array",
      "title": "Additional library search dirs",
      "items": {
        "type": "string"
      }
    },
    "tlas": {
      "type": "array",
      "title": "TLAS is a list of Jsonnet Top-level Arguments",
      "items": {
        "$ref": "_definitions.json#/definitions/v1alpha1JsonnetVar"
      }
    }
  },
  "$schema": "http://json-schema.org/schema#"
}